stauth/__init__.py
stauth/authenticate.py
stauth/util.py
stauth-0.1.11.dist-info/LICENSE
stauth-0.1.11.dist-info/WHEEL
stauth-0.1.11.dist-info/METADATA
stauth-0.1.11.dist-info/RECORD
